ask_football/__init__.py
ask_football/__main__.py
ask_football/cli.py
ask_football/main.py
Ask_FootBall-0.1.2.dist-info/LICENSE
Ask_FootBall-0.1.2.dist-info/METADATA
Ask_FootBall-0.1.2.dist-info/WHEEL
Ask_FootBall-0.1.2.dist-info/entry_points.txt
Ask_FootBall-0.1.2.dist-info/top_level.txt
Ask_FootBall-0.1.2.dist-info/RECORD
