Metadata-Version: 2.1
Name: Ask-FootBall
Version: 0.1.2
Summary: Ask me
Author-email: Kanishk Pachauri <itskanishkp.py@gmail.com>
License: MIT
Requires-Python: >=3.9
License-File: LICENSE
Requires-Dist: InquirerPy >=0.3.4
Requires-Dist: build >=1.0.3
Requires-Dist: twine >=4.0.2
